tabeline-0.6.2.dist-info/METADATA
tabeline-0.6.2.dist-info/WHEEL
tabeline-0.6.2.dist-info/licenses/LICENSE
tabeline/__init__.py
tabeline/_array.py
tabeline/_concatenate.py
tabeline/_data_frame.py
tabeline/_expression/__init__.py
tabeline/_expression/_parser.py
tabeline/_expression/_to_py_expression.py
tabeline/_expression/ast.py
tabeline/_record.py
tabeline/_tabeline.cpython-310-aarch64-linux-gnu.so
tabeline/exceptions.py
tabeline/testing.py
tabeline-0.6.2.dist-info/RECORD
