Metadata-Version: 2.4
Name: tabeline
Version: 0.6.2
Classifier: Development Status :: 4 - Beta
Classifier: Intended Audience :: Science/Research
Classifier: License :: OSI Approved :: MIT License
Classifier: Operating System :: POSIX :: Linux
Classifier: Operating System :: Microsoft :: Windows
Classifier: Operating System :: MacOS :: MacOS X
Classifier: Programming Language :: Python :: 3
Classifier: Programming Language :: Python :: 3.10
Classifier: Programming Language :: Python :: 3.11
Classifier: Programming Language :: Python :: 3.12
Classifier: Programming Language :: Python :: 3.13
Classifier: Programming Language :: Python :: Implementation :: CPython
Classifier: Programming Language :: Rust
Classifier: Topic :: Software Development :: Libraries :: Python Modules
Requires-Dist: parsita==2.*
Requires-Dist: pandas==2.* ; extra == 'pandas'
Requires-Dist: numpy ; extra == 'pandas'
Requires-Dist: pyarrow==21.* ; extra == 'pandas'
Requires-Dist: polars==1.* ; extra == 'polars'
Requires-Dist: pyarrow==21.* ; extra == 'polars'
Provides-Extra: pandas
Provides-Extra: polars
License-File: LICENSE
Summary: A data frame and data grammar library
Keywords: dataframe,datatable,datagrammar,dplyr
Author-email: David Hagen <david@drhagen.com>
License-Expression: MIT
Requires-Python: >=3.10, <4.0
Project-URL: Documentation, https://tabeline.drhagen.com
Project-URL: Repository, https://github.com/drhagen/tabeline
